[
    {
        "title":"G6 學者關係網絡：2010年~2018年間與「鄧維光」合作的學者"
    },
    [{    
        "name":"鄧維光", "value":40, "neighbors":11, "linkWidths":{
            "胡誌麟":2.5,
            "吳國光":2.5,
            "黃俊龍":2.5,
            "楊得年":2.5,
            "陳正君":2.5,
            "呂俊賢":2.5,
            "溫志煜":2.5,
            "侯廷偉":2.5,
            "廖俊睿":2.5,
            "黃仁暐":2.5,
            "葉彌妍":2.5
        },
        "children":[{
            "name":"溫志煜", "value":2, "neighbors":5,
            "link":["黃俊龍", "葉彌妍", "楊得年", "吳國光"], 
            "linkWidths": {
                "黃俊龍":0.8,
                "葉彌妍":0.8,
                "楊得年":0.8,
                "吳國光":0.8
            }
        },{
            "name":"陳正君", "value":2, "neighbors":3,
            "link":["呂俊賢", "楊得年"], 
            "linkWidths": {
                "呂俊賢":0.8,
                "楊得年":0.8
            }
        },{
            "name":"胡誌麟", "value":3, "neighbors":3,
            "link":["吳國光", "黃俊龍"], 
            "linkWidths": {
                "吳國光":0.8,
                "黃俊龍":0.8
            }
        },{
            "name":"黃俊龍", "value":3, "neighbors":5,
            "link":["溫志煜", "胡誌麟", "葉彌妍", "黃仁暐"], 
            "linkWidths": {
                "溫志煜":0.8,
                "胡誌麟":0.8,
                "葉彌妍":0.8,
                "黃仁暐":0.8
            }
        },{
            "name":"葉彌妍", "value":1, "neighbors":4,
            "link":["楊得年", "溫志煜", "黃俊龍"], 
            "linkWidths": {
                "楊得年":0.8,
                "溫志煜":0.8,
                "黃俊龍":0.8
            }
        },{
            "name":"廖俊睿", "value":2, "neighbors":2,
            "link":["黃仁暐"], 
            "linkWidths": {
                "黃仁暐":0.8
            }
        },{
            "name":"吳國光", "value":3, "neighbors":3,
            "link":["胡誌麟", "溫志煜"], 
            "linkWidths": {
                "胡誌麟":0.8,
                "溫志煜":0.8
            }
        },{
            "name":"楊得年", "value":2, "neighbors":5,
            "link":["呂俊賢", "葉彌妍", "陳正君", "溫志煜"], 
            "linkWidths": {
                "呂俊賢":0.8,
                "葉彌妍":0.8,
                "陳正君":0.8,
                "溫志煜":0.8
            }
        },{
            "name":"黃仁暐", "value":2, "neighbors":3,
            "link":["廖俊睿", "黃俊龍"], 
            "linkWidths": {
                "廖俊睿":0.8,
                "黃俊龍":0.8
            }
        },{
            "name":"侯廷偉", "value":2, "neighbors":1
        },{
            "name":"呂俊賢", "value":2, "neighbors":3,
            "link":["陳正君", "楊得年"], 
            "linkWidths": {
                "陳正君":0.8,
                "楊得年":0.8
            }
        }]            
    }]
]